flexp/__init__.py
flexp/csvfile.py
flexp/display.py
flexp/experiment.py
flexp/utils.py
flexp-50.0.dist-info/METADATA
flexp-50.0.dist-info/WHEEL
flexp-50.0.dist-info/namespace_packages.txt
flexp-50.0.dist-info/top_level.txt
flexp-50.0.dist-info/zip-safe
flexp-50.0.dist-info/RECORD
