Metadata-Version: 2.1
Name: flexp
Version: 50.0
Summary: UNKNOWN
Home-page: UNKNOWN
Author: UNKNOWN
Author-email: UNKNOWN
License: UNKNOWN
Platform: UNKNOWN
Classifier: Development Status :: 3 - Alpha
Classifier: Programming Language :: Python
Requires-Dist: psychopy
Requires-Dist: pygame
Requires-Dist: pyglet (==1.3)
